panacotta/__init__.py
panacotta-0.1.dist-info/DESCRIPTION.rst
panacotta-0.1.dist-info/METADATA
panacotta-0.1.dist-info/RECORD
panacotta-0.1.dist-info/WHEEL
panacotta-0.1.dist-info/metadata.json
panacotta-0.1.dist-info/top_level.txt
