Metadata-Version: 2.0
Name: panacotta
Version: 0.1
Summary: Python API for controlling Panasonic Blu-Ray players
Home-page: https://github.com/u1f35c/python-panacotta
Author: Jonathan McDowell
Author-email: noodles@earth.li
License: UNKNOWN
Platform: UNKNOWN
Classifier: Programming Language :: Python
Classifier: License :: OSI Approved :: GNU General Public License v3 or later (GPLv3+)
Classifier: Development Status :: 3 - Alpha
Classifier: Intended Audience :: Developers
Classifier: Operating System :: OS Independent
